importit/__init__.py
importit/importer.py
importit/util/__init__.py
importit/util/file.py
importit/util/module.py
importit-0.1.3.dist-info/LICENSE.txt
importit-0.1.3.dist-info/METADATA
importit-0.1.3.dist-info/WHEEL
importit-0.1.3.dist-info/top_level.txt
importit-0.1.3.dist-info/RECORD
