Metadata-Version: 2.1
Name: importit
Version: 0.1.3
Summary: Import python code from anywhere.
Home-page: https://github.com/divykj/importit
Author: Divya Jain
Author-email: dkj@somaiya.edu
License: MIT
Project-URL: Documentation, https://github.com/divykj/importit
Project-URL: Code, https://github.com/divykj/importit
Project-URL: Issue tracker, https://github.com/divykj/importit/issues
Platform: UNKNOWN
Classifier: Development Status :: 4 - Beta
Classifier: License :: OSI Approved :: MIT License
Classifier: Intended Audience :: Developers
Classifier: Topic :: Utilities
Classifier: Natural Language :: English
Classifier: Operating System :: OS Independent
Classifier: Programming Language :: Python
Classifier: Programming Language :: Python :: 3
Classifier: Programming Language :: Python :: 3.6
Classifier: Programming Language :: Python :: 3.7
Classifier: Programming Language :: Python :: 3.8
Classifier: Programming Language :: Python :: 3.9
Classifier: Programming Language :: Python :: 3 :: Only
Classifier: Programming Language :: Python :: Implementation :: CPython
Requires-Python: >=3.6
Provides-Extra: dev
Requires-Dist: black ; extra == 'dev'
Requires-Dist: flake8 ; extra == 'dev'
Requires-Dist: isort ; extra == 'dev'
Requires-Dist: pytest ; extra == 'dev'
Requires-Dist: pytest-cov ; extra == 'dev'
Requires-Dist: make-to-batch (>=0.2.3) ; extra == 'dev'
Provides-Extra: publish
Requires-Dist: twine ; extra == 'publish'
